python_roschat_bot/__init__.py
python_roschat_bot/bot.py
python_roschat_bot/enums.py
python_roschat_bot/exceptions.py
python_roschat_bot/schemas.py
python_roschat_bot/socket_handler.py
python_roschat_bot-0.1.1.dist-info/LICENSE
python_roschat_bot-0.1.1.dist-info/METADATA
python_roschat_bot-0.1.1.dist-info/WHEEL
python_roschat_bot-0.1.1.dist-info/RECORD
