Metadata-Version: 2.3
Name: python-roschat-bot
Version: 0.1.1
Summary: A Python library for creating bots for RosChat platform
License: MIT
Keywords: bot,roschat,socketio,messaging
Author: Vladislav Dorofeev
Author-email: vdorofeevdeveloper@gmail.com
Requires-Python: >=3.8.1
Classifier: Development Status :: 3 - Alpha
Classifier: Intended Audience :: Developers
Classifier: License :: OSI Approved :: MIT License
Classifier: Operating System :: OS Independent
Classifier: Programming Language :: Python :: 3
Classifier: Programming Language :: Python :: 3.8
Classifier: Programming Language :: Python :: 3.9
Classifier: Programming Language :: Python :: 3.10
Classifier: Programming Language :: Python :: 3.11
Classifier: Programming Language :: Python :: 3.12
Provides-Extra: dev
Requires-Dist: black (>=23.0) ; extra == "dev"
Requires-Dist: flake8 (>=6.0) ; extra == "dev"
Requires-Dist: pydantic (>=2.0.0,<3.0.0)
Requires-Dist: pydantic-settings (>=2.0.0,<3.0.0)
Requires-Dist: pylint (>=2.17) ; extra == "dev"
Requires-Dist: pytest (>=7.0) ; extra == "dev"
Requires-Dist: pytest-cov (>=4.0) ; extra == "dev"
Requires-Dist: python-socketio (>=5.0.0,<6.0.0)
Requires-Dist: requests (>=2.25.0,<3.0.0)
Requires-Dist: websocket-client (>=1.8.0,<2.0.0)
Project-URL: Documentation, https://github.com/FF7FSystem/python-roschat-bot#readme
Project-URL: Homepage, https://github.com/FF7FSystem/python-roschat-bot
Project-URL: Repository, https://github.com/FF7FSystem/python-roschat-bot
